mqtt_backend_serrawatch/MQTTPublisherClient.py
mqtt_backend_serrawatch/MqttClientManager.py
mqtt_backend_serrawatch/__init__.py
mqtt_backend_serrawatch/utils.py
mqtt_backend_serrawatch/data/BrokerConfig.py
mqtt_backend_serrawatch/data/Config.py
mqtt_backend_serrawatch/data/TopicsConfig.py
mqtt_backend_serrawatch-0.2.15.dist-info/METADATA
mqtt_backend_serrawatch-0.2.15.dist-info/WHEEL
mqtt_backend_serrawatch-0.2.15.dist-info/RECORD
