Metadata-Version: 2.3
Name: mqtt_backend_serrawatch
Version: 0.2.15
Summary: This project was created as part of the Internet of Things (IoT) course in the Master's program in Computer Architecture at the Haute École de la Province de Liège (HEPL).
Project-URL: Homepage, https://github.com/IOTSerraWatch/Client_OnUbuntu
Project-URL: Issues, https://github.com/IOTSerraWatch/Client_OnUbuntu/issues
Author-email: Alexandre Grzegorczyk <alexandregrzegorczyk2@gmail.com>
Classifier: License :: OSI Approved :: MIT License
Classifier: Operating System :: OS Independent
Classifier: Programming Language :: Python :: 3
Requires-Python: >=3.6
